{"paths":{"0":["jm_img_btn_common1_120_yellow",0],"1":["fruit/fruit_4",0],"2":["fruit/fruit_5",0],"3":["fruit/fruit_6",0],"4":["fruit/fruit_1",0],"5":["jm_bg_r48_ffffff",0],"6":["fruit/fruit_2",0],"7":["fruit/fruit_3",0],"8":["fruit/fruit_10",0],"9":["fruit/fruit_7",0],"10":["fruit/fruit_9",0],"11":["fruit/fruit_11",0],"12":["fruit/fruit_8",0],"13":["jm_img_bg_bai",0],"14":["fruit/fruit_4",1,1],"15":["fruit/fruit_6",1,1],"16":["jm_img_btn_common1_120_yellow",1,1],"17":["fruit/fruit_10",1,1],"18":["jm_bg_r48_ffffff",1,1],"19":["fruit/fruit_2",1,1],"20":["fruit/fruit_11",1,1],"21":["fruit/fruit_5",1,1],"22":["prefabs/WatermelonTips",2],"23":["fruit/fruit_9",1,1],"24":["fruit/fruit_8",1,1],"25":["jm_img_bg_bai",1,1],"26":["prefabs/WatermelonLayer",2],"27":["prefabs/WatermelonFruit",2],"28":["fruit/fruit_7",1,1],"29":["fruit/fruit_1",1,1],"30":["fruit/fruit_3",1,1]},"types":["cc.Texture2D","cc.SpriteFrame","cc.Prefab"],"uuids":["11TWg+lcRNorKad61zmgMZ","39NITcSbFCP5bzNO1zsFwS","3cGQnaMDRM+rWACB9BKzZe","440OPSRZFPaLZlJ1oQiTLi","470crk6cFLiq6oO+RTNr9g","6eUsKU9QFGo6r/HnlvMFKY","94fGCkezJFRqDbZjppey4X","94r8jWlrxCX63nctUr7jRv","951iSD1rRLVYasn5SVpywk","9a0OUpkg1K7oZB+XqVb7Jt","abr5RybvlI/L3NBZ24x5ex","c4/0XZ0iJOoaYutNyeXGlQ","c9soUvMUhE06R15DMqrrcq","e8TkOJNmpEha3o49w4nVh1","02DxxeehdPEZYHGnBR8s1V","0djWByk3BAy5TkDdKHwCNL","0e1XFecx5JULZ+5Mb6O4gs","15WFL7/fxOSqRitjFi4nng","158bPmb/BDkqlO6CT9qfgE","1fCVxQu7FGjqyhJa/LAGmC","35vCvbXHlPprapVSJ/i0Bd","38RnispedHiJllvrC1lKJe","434TVvpdVItoS1HFlNWKNQ","4bkz723sZLkITpfM9ZUmxy","5fWdc3O1FASr3ul1JAXki8","85GaoDg3RGep5cloGT+r0A","8cYDzxqKlJ4qUmasKArIkt","a61EKQLUxOyJm+pjzmruG0","c3xcBf1f1JIb85uZQIZ1UF","c8LVOyEjFK7r+TbLzkT4Lg","f0oEdiOpVPhKsRUeMvPML9","ecpdLyjvZBwrvm+cedCcQy"],"scenes":{},"redirect":[31,0],"deps":["internal"],"packs":{"04ed9dc38":[16,18,22,25],"09fe3ac11":[0,1,2,3,4,5,6,7,8,9,10,11,12,13],"0b7cee2c9":[20,27]},"name":"resources","importBase":"import","nativeBase":"native","debug":false,"isZip":false,"encrypted":false,"versions":{"import":[14,"78dbb","04ed9dc38","a0314","09fe3ac11","1a978","0b7cee2c9","50bdf",15,"8836b",17,"6aeab",19,"f03d8",21,"7bb36",23,"67b71",24,"4ffeb",26,"ececb",28,"8f89b",29,"67e1d",30,"684e8"],"native":[0,"31597",1,"53975",2,"60d08",3,"defe3",4,"fc014",5,"0cef8",6,"17fd0",7,"2565f",8,"70792",9,"db02a",10,"8c363",11,"d389b",12,"b3586",13,"37f5b"]}}